setup.py
sciurus/__init__.py
sciurus/scheduler.py
sciurus.egg-info/PKG-INFO
sciurus.egg-info/SOURCES.txt
sciurus.egg-info/dependency_links.txt
sciurus.egg-info/top_level.txt