Metadata-Version: 1.0
Name: sciurus
Version: 0.1.0
Summary: An minimalist function scheduler
Home-page: https://github.com/elric-dev/sciurus
Author: elric-dev
Author-email: hsalee101@gmail.com
License: MIT
Keywords: scheduler
Platform: UNKNOWN
